[
  {
    "title": "The Legend of Zelda: Breath of the Wild",
    "platform": "Nintendo Switch",
    "release_date": "2017г",
    "status": "Отлично (требует настройки графики)"
  },
  {
    "title": "God of War II",
    "platform": "PS2",
    "release_date": "2007г",
    "status": "Идеально"
  },
  {
    "title": "Super Mario Galaxy",
    "platform": "Wii",
    "release_date": "2007г",
    "status": "Стабильно (60 FPS)"
  },
  {
    "title": "Demon's Souls",
    "platform": "PS3",
    "release_date": "2009г",
    "status": "Хорошо (незначительные лаги)"
  },
  {
    "title": "Metal Gear Solid 4: Guns of the Patriots",
    "platform": "PS3",
    "release_date": "2008г",
    "status": "Играбельно (требует мощного GPU)"
  },
  {
    "title": "The Legend of Zelda: Ocarina of Time 3D",
    "platform": "Nintendo 3DS",
    "release_date": "2011г",
    "status": "Отлично"
  },
  {
    "title": "GoldenEye 007",
    "platform": "Nintendo 64",
    "release_date": "1997г",
    "status": "Стабильно"
  },
  {
    "title": "Halo: Combat Evolved",
    "platform": "Xbox",
    "release_date": "2001г",
    "status": "Хорошо (проблемы со звуком)"
  },
  {
    "title": "Tekken 3",
    "platform": "PlayStation",
    "release_date": "1998г",
    "status": "Идеально"
  },
  {
    "title": "Final Fantasy Tactics Advance",
    "platform": "Game Boy Advance",
    "release_date": "2003г",
    "status": "Без проблем"
  }
]
